onto_crawler/__init__.py
onto_crawler/__main__.py
onto_crawler/api.py
onto_crawler/cli.py
onto_crawler/version.py
onto_crawler-0.1.11.dist-info/entry_points.txt
onto_crawler-0.1.11.dist-info/LICENSE
onto_crawler-0.1.11.dist-info/WHEEL
onto_crawler-0.1.11.dist-info/METADATA
onto_crawler-0.1.11.dist-info/RECORD
